earlysign/__init__.py
earlysign/__version__.py
earlysign/api/__init__.py
earlysign/api/compatibility/__init__.py
earlysign/core/__init__.py
earlysign/infra/__init__.py
earlysign/stats/__init__.py
earlysign/stats/common/__init__.py
earlysign/stats/common/anytime_valid/__init__.py
earlysign/stats/common/group_sequential/__init__.py
earlysign/stats/means/__init__.py
earlysign/stats/proportions/__init__.py
earlysign/stats/survival/__init__.py
earlysign-0.2.0.dist-info/LICENSE
earlysign-0.2.0.dist-info/METADATA
earlysign-0.2.0.dist-info/WHEEL
earlysign-0.2.0.dist-info/RECORD
