Metadata-Version: 2.3
Name: earlysign
Version: 0.2.0
Summary: Early signs, faster decisions. A Python library for sequential/safe testing (alpha-spending, e-processes, etc.).
License: Apache-2.0
Author: Takeshi Teshima
Author-email: takeshi.78.teshima@gmail.com
Requires-Python: >=3.11,<4.0
Classifier: License :: OSI Approved :: Apache Software License
Classifier: Programming Language :: Python :: 3
Classifier: Programming Language :: Python :: 3.11
Classifier: Programming Language :: Python :: 3.12
Classifier: Programming Language :: Python :: 3.13
Provides-Extra: examples
Requires-Dist: matplotlib (>=3.10.6,<4.0.0) ; extra == "examples"
Requires-Dist: numpy (>=2.3.2,<3.0.0) ; extra == "examples"
Requires-Dist: scipy (>=1.16.1,<2.0.0)
Project-URL: Homepage, https://early-sign.github.io/EarlySign
Project-URL: Repository, https://github.com/early-sign/EarlySign
